CHANGELOG.md
LICENSE
MANIFEST.in
README.rst
setup.cfg
setup.py
bin/nuoca
etc/nuoca.yml
etc/nuoca_env.sh
etc/nuoca_export.sh
etc/nuoca_settings.yml
etc/nuoca_setup.sh
pynuoca/__init__.py
pynuoca/nuoca.py
pynuoca/nuoca_config.py
pynuoca/nuoca_plugin.py
pynuoca/nuoca_util.py
pynuoca.egg-info/PKG-INFO
pynuoca.egg-info/SOURCES.txt
pynuoca.egg-info/dependency_links.txt
pynuoca.egg-info/requires.txt
pynuoca.egg-info/top_level.txt
pynuoca/lib/__init__.py
pynuoca/lib/metrics_influx.py
pynuoca/nuomon/__init__.py
pynuoca/nuomon/nuomon_broadcast.py
pynuoca/nuomon/nuomon_monitor.py
pynuoca/nuomon/nuomon_util.py
pynuoca/plugins/__init__.py
pynuoca/plugins/input/Counter.multiprocess-plugin
pynuoca/plugins/input/Counter2.multiprocess-plugin
pynuoca/plugins/input/CounterPlugin.py
pynuoca/plugins/input/Dbt2.multiprocess-plugin
pynuoca/plugins/input/Dbt2Plugin.py
pynuoca/plugins/input/LogstashPlugin.py
pynuoca/plugins/input/NuoAdminAgentLog.multiprocess-plugin
pynuoca/plugins/input/NuoAdminMonitor.multiprocess-plugin
pynuoca/plugins/input/NuoAdminMonitorPlugin.py
pynuoca/plugins/input/NuoAdminNuoMonitor.multiprocess-plugin
pynuoca/plugins/input/NuoAdminNuoMonitorPlugin.py
pynuoca/plugins/input/NuoMonitor.multiprocess-plugin
pynuoca/plugins/input/NuoMonitorPlugin.py
pynuoca/plugins/input/NuoSimpleDriver.multiprocess-plugin
pynuoca/plugins/input/OLTPBench.multiprocess-plugin
pynuoca/plugins/input/OLTPBenchPlugin.py
pynuoca/plugins/input/Zabbix.multiprocess-plugin
pynuoca/plugins/input/ZabbixPlugin.py
pynuoca/plugins/input/__init__.py
pynuoca/plugins/output/ElasticSearch.multiprocess-plugin
pynuoca/plugins/output/ElasticSearchPlugin.py
pynuoca/plugins/output/File.multiprocess-plugin
pynuoca/plugins/output/FilePlugin.py
pynuoca/plugins/output/InfluxDBPlugin.multiprocess-plugin
pynuoca/plugins/output/InfluxDBPlugin.py
pynuoca/plugins/output/KafkaProducerPlugin.multiprocess-plugin
pynuoca/plugins/output/KafkaProducerPlugin.py
pynuoca/plugins/output/Printer.multiprocess-plugin
pynuoca/plugins/output/PrinterPlugin.py
pynuoca/plugins/output/RestClient.multiprocess-plugin
pynuoca/plugins/output/RestClientPlugin.py
