Metadata-Version: 1.1
Name: pynuoca
Version: 20.0.3
Summary: NuoDB Collection Agent (NuoCA)
Home-page: https://github.com/nuodb/nuoca
Author: NuoDB
Author-email: support@nuodb.com
License: MIT
Keywords: nuodb scalable cloud database
Platform: UNKNOWN
Classifier: Development Status :: 5 - Production/Stable
Classifier: Environment :: Console
Classifier: Intended Audience :: Developers
Classifier: Programming Language :: Python
Classifier: Programming Language :: Python :: 2
Classifier: Programming Language :: Python :: 2.7
Classifier: License :: OSI Approved :: MIT License
Classifier: Operating System :: POSIX
Classifier: Topic :: Database :: Front-Ends
